LICENSE
MANIFEST.in
README.md
requirements.txt
setup.py
django_trusts.egg-info/PKG-INFO
django_trusts.egg-info/SOURCES.txt
django_trusts.egg-info/dependency_links.txt
django_trusts.egg-info/not-zip-safe
django_trusts.egg-info/requires.txt
django_trusts.egg-info/top_level.txt
tests/__init__.py
tests/runtests.py
tests/settings.py
tests/urls.py
trusts/__init__.py
trusts/__init__.pyc
trusts/admin.py
trusts/admin.pyc
trusts/apps.py
trusts/apps.pyc
trusts/backends.py
trusts/backends.pyc
trusts/decorators.py
trusts/decorators.pyc
trusts/models.py
trusts/models.pyc
trusts/tests.py
trusts/tests.pyc
trusts/utils.py
trusts/utils.pyc
trusts/management/__init__.py
trusts/management/__init__.pyc
trusts/management/commands/__init__.py
trusts/management/commands/__init__.pyc
trusts/management/commands/create_trust_root.py
trusts/management/commands/create_trust_root.pyc
trusts/management/commands/update_roles_permissions.py
trusts/management/commands/update_roles_permissions.pyc
trusts/migrations/0001_initial.py
trusts/migrations/0001_initial.pyc
trusts/migrations/__init__.py
trusts/migrations/__init__.pyc