Metadata-Version: 1.1
Name: django-trusts
Version: 0.10.3
Summary: Django authorization add-on for multiple organizations and object-level permission settings
Home-page: http://github.com/beedesk/django-trusts
Author: Thomas Yip
Author-email: thomasleaf@gmail.com
License: BSD 2-Clause
Platform: UNKNOWN
Classifier: Development Status :: 4 - Beta
Classifier: Framework :: Django :: 1.8
Classifier: Intended Audience :: Developers
Classifier: Intended Audience :: Information Technology
Classifier: Intended Audience :: System Administrators
Classifier: License :: OSI Approved :: BSD License
Classifier: Natural Language :: English
Classifier: Operating System :: OS Independent
Classifier: Programming Language :: Python
Classifier: Programming Language :: Python :: 2
Classifier: Topic :: Software Development :: Libraries
